coreml/__init__.py
coreml/config.py
coreml/factory.py
coreml/trainer.py
coreml/data/__init__.py
coreml/data/base_dataset.py
coreml/data/classification.py
coreml/data/data_module.py
coreml/data/dataloader.py
coreml/data/sampler.py
coreml/data/transforms.py
coreml/data/utils.py
coreml/data/process/CIFAR10.py
coreml/data/process/CIFAR100.py
coreml/data/process/__init__.py
coreml/data/vision/__init__.py
coreml/data/vision/base.py
coreml/data/vision/image.py
coreml/modules/__init__.py
coreml/modules/activations.py
coreml/modules/classification.py
coreml/modules/decomposition.py
coreml/modules/init.py
coreml/modules/layers.py
coreml/modules/nn.py
coreml/modules/optimization.py
coreml/modules/sklearn.py
coreml/modules/backbones/__init__.py
coreml/modules/backbones/base.py
coreml/modules/backbones/efficientnet.py
coreml/modules/backbones/resnet.py
coreml/modules/backbones/resnet_swsl.py
coreml/modules/backbones/utils.py
coreml/modules/backbones/vgg.py
coreml/utils/__init__.py
coreml/utils/array.py
coreml/utils/checkpoint.py
coreml/utils/io.py
coreml/utils/logger.py
coreml/utils/loss.py
coreml/utils/metrics.py
coreml/utils/typing.py
coreml/utils/viz.py
coreml/utils/wandb.py
coreml-0.0.15.dist-info/METADATA
coreml-0.0.15.dist-info/RECORD
coreml-0.0.15.dist-info/WHEEL
coreml-0.0.15.dist-info/top_level.txt
evaluation/__init__.py
evaluation/eval.py
tests/__init__.py
tests/test_config.py
tests/data/__init__.py
tests/data/test_classification_dataset.py
tests/data/test_classification_transform.py
tests/data/test_data_module.py
tests/data/test_dataloader.py
tests/data/test_sampler.py
tests/data/test_transforms.py
tests/data/test_utils.py
tests/modules/__init__.py
tests/modules/test_activations.py
tests/modules/test_classification_metrics.py
tests/modules/test_layers.py
tests/modules/test_nn_network.py
tests/modules/test_optimizer.py
tests/trainer/__init__.py
tests/trainer/test_checkpoint_loading.py
tests/trainer/test_classification.py
tests/utils/__init__.py
tests/utils/test_array.py
tests/utils/test_metrics.py
tests/utils/test_wandb.py
