Metadata-Version: 2.1
Name: coreml
Version: 0.0.15
Summary: Generic Framework for ML projects
Home-page: https://github.com/dalmia/coreml
Author: Aman Dalmia
Author-email: amandalmia18@gmail.com
License: UNKNOWN
Platform: UNKNOWN
Classifier: Programming Language :: Python :: 3
Classifier: License :: OSI Approved :: MIT License
Classifier: Operating System :: OS Independent
Requires-Python: >=3.6
Requires-Dist: matplotlib (==3.2.1)
Requires-Dist: natsort (==7.0.1)
Requires-Dist: opencv-python
Requires-Dist: pandas (==1.0.3)
Requires-Dist: Pillow (==7.1.1)
Requires-Dist: PyYAML (>=5.1)
Requires-Dist: scikit-learn (==0.22.2.post1)
Requires-Dist: termcolor (==1.1.0)
Requires-Dist: torch (==1.6.0)
Requires-Dist: torchsummary (==1.5.1)
Requires-Dist: torchtext (==0.4.0)
Requires-Dist: torchvision (==0.7.0)
Requires-Dist: torchaudio (==0.6.0)
Requires-Dist: tqdm (==4.45.0)
Requires-Dist: wandb (==0.9.4)
Requires-Dist: xgboost (==1.1.1)
Requires-Dist: timm (==0.2.1)
Requires-Dist: pytorch-lightning (==0.9.0)
Requires-Dist: kornia (==0.4.0)
